alectors/__init__.py
alectors/ppo/__init__.py
alectors/ppo/agent.py
alectors-2.0.3.dist-info/LICENSES/GPLv3.txt
alectors-2.0.3.dist-info/LICENSES/TPLv1.txt
alectors-2.0.3.dist-info/METADATA
alectors-2.0.3.dist-info/WHEEL
alectors-2.0.3.dist-info/RECORD
