Metadata-Version: 2.3
Name: alectors
Version: 2.0.3
Summary: transformer-based rl agents for nlp tasks
Author: Vasilis Valatsos
Author-email: aethrvmn@apotheke.earth
Requires-Python: >=3.13
Classifier: Programming Language :: Python :: 3
Classifier: Programming Language :: Python :: 3.13
Requires-Dist: numpy (>=2.2.5,<3.0.0)
Requires-Dist: telestes (>=0.1.2,<0.2.0)
Requires-Dist: torch (>=2.6)
Requires-Dist: transformers (>=4.51.3,<5.0.0)
